fcship/__init__.py
fcship/cli.py
fcship/commands/__init__.py
fcship/commands/api.py
fcship/commands/db.py
fcship/commands/docs.py
fcship/commands/domain.py
fcship/commands/project.py
fcship/commands/repo.py
fcship/commands/service.py
fcship/commands/test.py
fcship/commands/verify.py
fcship/commands/commit/__init__.py
fcship/commands/commit/commit.py
fcship/commands/commit/commit_types.py
fcship/commands/commit/generate_commit_message.py
fcship/commands/commit/utils.py
fcship/commands/compact/__init__.py
fcship/commands/compact/__main__.py
fcship/commands/compact/ast_utils.py
fcship/commands/compact/cli.py
fcship/commands/compact/compact.py
fcship/commands/compact/compact_code_visitor.py
fcship/commands/compact/compactors.py
fcship/commands/compact/config.py
fcship/commands/compact/file_utils.py
fcship/commands/compact/generator.py
fcship/commands/compact/token_counter.py
fcship/commands/github/__init__.py
fcship/commands/github/cli.py
fcship/commands/github/github_utils.py
fcship/commands/github/main.py
fcship/commands/github/setup.py
fcship/templates/__init__.py
fcship/templates/api_templates.py
fcship/templates/domain_templates.py
fcship/templates/project_templates.py
fcship/templates/repo_templates.py
fcship/templates/service_templates.py
fcship/templates/test_templates.py
fcship/tests/conftest.py
fcship/tui/__init__.py
fcship/tui/display.py
fcship/tui/errors.py
fcship/tui/extra.py
fcship/tui/helpers.py
fcship/tui/input.py
fcship/tui/menu.py
fcship/tui/panels.py
fcship/tui/progress.py
fcship/tui/tables.py
fcship/tui/types.py
fcship/utils/__init__.py
fcship/utils/docstring_example.py
fcship/utils/error_handling.py
fcship/utils/file_utils.py
fcship/utils/functional.py
fcship/utils/type_utils.py
fcship/utils/validation.py
fast_craftsmanship-0.2.6.dist-info/LICENSE
fast_craftsmanship-0.2.6.dist-info/METADATA
fast_craftsmanship-0.2.6.dist-info/WHEEL
fast_craftsmanship-0.2.6.dist-info/entry_points.txt
fast_craftsmanship-0.2.6.dist-info/top_level.txt
fast_craftsmanship-0.2.6.dist-info/RECORD
