Metadata-Version: 2.2
Name: fast-craftsmanship
Version: 0.2.6
Summary: Add your description here
Requires-Python: >=3.12
License-File: LICENSE
Requires-Dist: expression>=5.6.0
Requires-Dist: hypothesis>=6.127.1
Requires-Dist: pydantic>=2.10.6
Requires-Dist: pygithub>=2.6.1
Requires-Dist: pytest>=8.3.4
Requires-Dist: pytest-asyncio>=0.25.3
Requires-Dist: pytest-cov>=6.0.0
Requires-Dist: pytest-mock>=3.14.0
Requires-Dist: questionary>=2.0.1
Requires-Dist: tiktoken>=0.9.0
Requires-Dist: typer>=0.15.1
Requires-Dist: rich-click>=1.8.3
Requires-Dist: pyyaml>=6.0.1
